p2p_copy/__init__.py
p2p_copy/api.py
p2p_copy/compressor.py
p2p_copy/io_utils.py
p2p_copy/protocol.py
p2p_copy/security.py
p2p_copy_cli/main.py
p2p_copy_server/__init__.py
p2p_copy_server/relay.py
p2p_copy-0.1.2.dist-info/METADATA
p2p_copy-0.1.2.dist-info/WHEEL
p2p_copy-0.1.2.dist-info/entry_points.txt
p2p_copy-0.1.2.dist-info/licenses/LICENSE
p2p_copy-0.1.2.dist-info/RECORD
