Metadata-Version: 2.4
Name: p2p-copy
Version: 0.1.2
Summary: Python library and command-line tool for transferring files and directories over a WebSocket relay server
Author: AfuLD
License: MIT
License-File: LICENSE
Keywords: file-transfer,p2p,websocket
Classifier: Development Status :: 3 - Alpha
Classifier: License :: OSI Approved :: MIT License
Classifier: Programming Language :: Python :: 3
Classifier: Programming Language :: Python :: 3 :: Only
Classifier: Typing :: Typed
Requires-Python: >=3.10
Requires-Dist: typer>=0.12
Requires-Dist: websockets>=15.0.1
Requires-Dist: zstandard>=0.22
Provides-Extra: dev
Requires-Dist: mkdocs-material>=9.6.20; extra == 'dev'
Requires-Dist: mkdocs>=1.6.1; extra == 'dev'
Requires-Dist: mkdocstrings-python>=1.18.2; extra == 'dev'
Requires-Dist: pytest>=8.4.1; extra == 'dev'
Provides-Extra: security
Requires-Dist: argon2-cffi>=21.1; extra == 'security'
Requires-Dist: cryptography>=42.0; extra == 'security'
